aac_req_qa/__init__.py
aac_req_qa/ai_prompts.py
aac_req_qa/ai_util.py
aac_req_qa/req_qa.aac
aac_req_qa/req_qa_impl.py
aac_req_qa-0.3.1.dist-info/LICENSE
aac_req_qa-0.3.1.dist-info/METADATA
aac_req_qa-0.3.1.dist-info/WHEEL
aac_req_qa-0.3.1.dist-info/entry_points.txt
aac_req_qa-0.3.1.dist-info/top_level.txt
aac_req_qa-0.3.1.dist-info/RECORD
