Metadata-Version: 2.1
Name: aac-req-qa
Version: 0.3.1
Home-page: https://github.com/DevOps-MBSE/AaC-Req-QA
License: MIT License
Keywords: MBSE,Requirements,QA
Classifier: Programming Language :: Python :: 3.10
Classifier: License :: OSI Approved :: MIT License
Classifier: Operating System :: OS Independent
Classifier: Topic :: Scientific/Engineering
License-File: LICENSE
Requires-Dist: aac ~=0.4.8
Requires-Dist: openai ~=1.30.5
Provides-Extra: test
Requires-Dist: build >=1.0.0 ; extra == 'test'
Requires-Dist: tox >=3.24 ; extra == 'test'
Requires-Dist: nose2 ~=0.10.0 ; extra == 'test'
Requires-Dist: coverage ~=6.0 ; extra == 'test'
Requires-Dist: flake8 ~=4.0 ; extra == 'test'
Requires-Dist: flake8-docstrings ~=1.6.0 ; extra == 'test'
Requires-Dist: flake8-fixme ~=1.1.1 ; extra == 'test'
Requires-Dist: flake8-eradicate ~=1.2.0 ; extra == 'test'
Requires-Dist: flake8-assertive ~=1.3.0 ; extra == 'test'
